pyjsaw/__init__.py
pyjsaw/ast_print.py
pyjsaw/baselib.py
pyjsaw/compiler.py
pyjsaw/def_modules.py
pyjsaw/stream.py
pyjsaw/utils.py
pyjsaw/js_stuff/__init__.py
pyjsaw/js_stuff/html.py
pyjsaw/js_stuff/vuestuff.py
pyjsaw/pyjs/__init__.py
pyjsaw/pyjs/vcollector.py
pyjsaw/typing/__init__.py
pyjsaw/typing/jstyping.py
pyjsaw/typing/vuetyping.py
pyjsaw-1.1.0.dist-info/LICENSE
pyjsaw-1.1.0.dist-info/METADATA
pyjsaw-1.1.0.dist-info/WHEEL
pyjsaw-1.1.0.dist-info/top_level.txt
pyjsaw-1.1.0.dist-info/RECORD
