Metadata-Version: 2.1
Name: pyjsaw
Version: 1.1.0
Summary: pyjsaw - python to javascript compiler with integrated Vue support
Author-email: Valery Kucherov <valq7711@gmail.com>
License: MIT License
Project-URL: homepage, https://github.com/valq7711/pyjsaw
Project-URL: repository, https://github.com/valq7711/pyjsaw
Keywords: python,webapplication,vue,javascript,js
Classifier: Development Status :: 3 - Alpha
Classifier: Environment :: Web Environment
Classifier: Intended Audience :: Developers
Classifier: License :: OSI Approved :: MIT License
Classifier: Operating System :: OS Independent
Classifier: Programming Language :: Python :: 3.7
Classifier: Programming Language :: Python :: 3.8
Classifier: Programming Language :: Python :: 3.9
Classifier: Programming Language :: Python :: 3.10
Classifier: Topic :: Internet :: WWW/HTTP :: Dynamic Content
Classifier: Topic :: Software Development :: Libraries :: Python Modules
Requires-Python: >=3.8
License-File: LICENSE
